django_mustache/__init__.py
django_mustache/engine.py
django_mustache-1.1.2.dist-info/LICENSE
django_mustache-1.1.2.dist-info/METADATA
django_mustache-1.1.2.dist-info/WHEEL
django_mustache-1.1.2.dist-info/top_level.txt
django_mustache-1.1.2.dist-info/RECORD
